osyris/__init__.py
osyris/config/__init__.py
osyris/config/defaults.py
osyris/core/__init__.py
osyris/core/array.py
osyris/core/base.py
osyris/core/datagroup.py
osyris/core/dataset.py
osyris/core/layer.py
osyris/core/plot.py
osyris/core/tools.py
osyris/core/vector.py
osyris/io/__init__.py
osyris/io/amr.py
osyris/io/grav.py
osyris/io/hilbert.py
osyris/io/hydro.py
osyris/io/loader.py
osyris/io/part.py
osyris/io/ramses.py
osyris/io/reader.py
osyris/io/rt.py
osyris/io/sink.py
osyris/io/utils.py
osyris/plot/__init__.py
osyris/plot/direction.py
osyris/plot/hist1d.py
osyris/plot/hist2d.py
osyris/plot/map.py
osyris/plot/parser.py
osyris/plot/plot.py
osyris/plot/render.py
osyris/plot/scatter.py
osyris/plot/wrappers.py
osyris/spatial/__init__.py
osyris/spatial/subdomain.py
osyris/units/__init__.py
osyris/units/library.py
osyris/units/units.py
osyris-3.1.0.dist-info/licenses/LICENSE
osyris-3.1.0.dist-info/METADATA
osyris-3.1.0.dist-info/WHEEL
osyris-3.1.0.dist-info/top_level.txt
osyris-3.1.0.dist-info/RECORD
