Metadata-Version: 2.4
Name: osyris
Version: 3.1.0
Summary: A package to visualize AMR data from the RAMSES code
Author: Neil Vaytet
License: BSD 3-Clause License
Project-URL: Bug Tracker, https://github.com/osyris-project/osyris/issues
Project-URL: Documentation, https://osyris.readthedocs.io
Project-URL: Source, https://github.com/osyris-project/osyris
Classifier: Intended Audience :: Science/Research
Classifier: License :: OSI Approved :: BSD License
Classifier: Natural Language :: English
Classifier: Operating System :: OS Independent
Classifier: Programming Language :: Python :: 3
Classifier: Programming Language :: Python :: 3 :: Only
Classifier: Programming Language :: Python :: 3.9
Classifier: Programming Language :: Python :: 3.10
Classifier: Programming Language :: Python :: 3.11
Classifier: Programming Language :: Python :: 3.12
Classifier: Programming Language :: Python :: 3.13
Requires-Python: >=3.9
License-File: LICENSE
Requires-Dist: matplotlib
Requires-Dist: numba
Requires-Dist: numpy
Requires-Dist: pint>=0.22
Dynamic: license-file
